firexkit/__init__.py
firexkit/_version.py
firexkit/argument_conversion.py
firexkit/bag_of_goodies.py
firexkit/broker.py
firexkit/chain.py
firexkit/firex_exceptions.py
firexkit/firexkit_common.py
firexkit/inspect.py
firexkit/memory_utils.py
firexkit/permissions.py
firexkit/proc_utils.py
firexkit/resources.py
firexkit/result.py
firexkit/revoke.py
firexkit/task.py
firexkit/install_resources/cloud-ci-install-configs.json
firexkit/resources/firex.css
firexkit/resources/firex_logo.png
firexkit/templates/link.html
firexkit/templates/log_template.html
firexkit-5.2.23.dist-info/LICENSE
firexkit-5.2.23.dist-info/METADATA
firexkit-5.2.23.dist-info/WHEEL
firexkit-5.2.23.dist-info/entry_points.txt
firexkit-5.2.23.dist-info/top_level.txt
firexkit-5.2.23.dist-info/zip-safe
firexkit-5.2.23.dist-info/RECORD
