Metadata-Version: 2.1
Name: firexkit
Version: 5.2.23
Summary: Core firex libraries
Home-page: https://github.com/FireXStuff/firexkit
Author: Core FireX Team
Author-email: firex-dev@gmail.com
License: BSD-3-Clause
Platform: UNKNOWN
License-File: LICENSE
Requires-Dist: celery==5.3.1
Requires-Dist: jinja2
Requires-Dist: pydantic==2.12.0
